LICENSE
MANIFEST.in
README.md
setup.py
djangoplus_documentos.egg-info/PKG-INFO
djangoplus_documentos.egg-info/SOURCES.txt
djangoplus_documentos.egg-info/dependency_links.txt
djangoplus_documentos.egg-info/requires.txt
djangoplus_documentos.egg-info/top_level.txt
documentos/__init__.py
documentos/models.py
documentos/migrations/0001_initial.py
documentos/migrations/0002_auto_20190325_1034.py
documentos/migrations/__init__.py
documentos/migrations/__pycache__/0001_initial.cpython-37.pyc
documentos/migrations/__pycache__/0002_auto_20190325_1034.cpython-37.pyc
documentos/migrations/__pycache__/__init__.cpython-37.pyc
documentos/static/.DS_Store
documentos/static/js/certidao.js