Metadata-Version: 1.1
Name: djangoplus-documentos
Version: 0.3
Summary: A simple djangoplus application that contains classes for some document types used in Brazil
Home-page: http://djangoplus.net/
Author: Breno Silva
Author-email: brenokcc@yahoo.com.br
License: BSD License
Platform: UNKNOWN
Classifier: Environment :: Web Environment
Classifier: Framework :: Django
Classifier: Intended Audience :: Developers
Classifier: License :: OSI Approved :: BSD License
Classifier: Operating System :: OS Independent
Classifier: Programming Language :: Python
Classifier: Topic :: Internet :: WWW/HTTP
Classifier: Topic :: Internet :: WWW/HTTP :: Dynamic Content
